{
  "topics": [
    {
      "id": "food",
      "name": "음식 월드컵",
      "emoji": "🍜",
      "description": "최고의 음식을 골라보세요!",
      "candidates": [
        { "id": 1, "name": "치킨", "emoji": "🍗", "desc": "바삭한 후라이드 & 양념" },
        { "id": 2, "name": "피자", "emoji": "🍕", "desc": "치즈가 듬뿍" },
        { "id": 3, "name": "떡볶이", "emoji": "🌶️", "desc": "매콤달콤 국민 간식" },
        { "id": 4, "name": "삼겹살", "emoji": "🥓", "desc": "불판 위의 황금 고기" },
        { "id": 5, "name": "초밥", "emoji": "🍣", "desc": "신선한 해산물의 정수" },
        { "id": 6, "name": "라면", "emoji": "🍜", "desc": "밤에 먹으면 더 맛있는" },
        { "id": 7, "name": "햄버거", "emoji": "🍔", "desc": "두툼한 패티와 신선한 채소" },
        { "id": 8, "name": "파스타", "emoji": "🍝", "desc": "크리미한 알프레도" },
        { "id": 9, "name": "김치찌개", "emoji": "🍲", "desc": "얼큰하고 뜨끈한 국물" },
        { "id": 10, "name": "비빔밥", "emoji": "🥗", "desc": "알록달록 영양 가득" },
        { "id": 11, "name": "짜장면", "emoji": "🍜", "desc": "검은 소스의 마력" },
        { "id": 12, "name": "냉면", "emoji": "🍥", "desc": "시원한 여름 별미" },
        { "id": 13, "name": "불고기", "emoji": "🥩", "desc": "달콤한 간장 양념" },
        { "id": 14, "name": "돈까스", "emoji": "🍱", "desc": "바삭한 튀김옷" },
        { "id": 15, "name": "마라탕", "emoji": "🌶️", "desc": "얼얼한 사천 향신료" },
        { "id": 16, "name": "탕수육", "emoji": "🍖", "desc": "새콤달콤 부먹 vs 찍먹" }
      ]
    },
    {
      "id": "travel",
      "name": "여행지 월드컵",
      "emoji": "✈️",
      "description": "가장 가고 싶은 여행지는?",
      "candidates": [
        { "id": 1, "name": "제주도", "emoji": "🌊", "desc": "한라산과 에메랄드 바다" },
        { "id": 2, "name": "파리", "emoji": "🗼", "desc": "낭만의 에펠탑 도시" },
        { "id": 3, "name": "도쿄", "emoji": "🗾", "desc": "첨단과 전통의 공존" },
        { "id": 4, "name": "뉴욕", "emoji": "🗽", "desc": "잠들지 않는 도시" },
        { "id": 5, "name": "방콕", "emoji": "🛺", "desc": "맛과 사원의 나라" },
        { "id": 6, "name": "발리", "emoji": "🌺", "desc": "신들의 섬 리조트" },
        { "id": 7, "name": "하와이", "emoji": "🌈", "desc": "태평양의 낙원" },
        { "id": 8, "name": "런던", "emoji": "🎡", "desc": "빅벤과 버킹엄 궁전" },
        { "id": 9, "name": "바르셀로나", "emoji": "🏟️", "desc": "가우디 건축의 도시" },
        { "id": 10, "name": "로마", "emoji": "🏛️", "desc": "영원한 역사의 도시" },
        { "id": 11, "name": "스위스", "emoji": "🏔️", "desc": "알프스 설원과 초원" },
        { "id": 12, "name": "부산", "emoji": "🌉", "desc": "광안리와 해운대" },
        { "id": 13, "name": "몰디브", "emoji": "🏝️", "desc": "수상 빌라의 천국" },
        { "id": 14, "name": "시드니", "emoji": "🦘", "desc": "오페라하우스와 항구" },
        { "id": 15, "name": "프라하", "emoji": "🏰", "desc": "동화 같은 구시가지" },
        { "id": 16, "name": "두바이", "emoji": "🌆", "desc": "사막 위의 미래 도시" }
      ]
    },
    {
      "id": "animal",
      "name": "동물 월드컵",
      "emoji": "🐾",
      "description": "가장 귀여운 동물을 뽑아보세요!",
      "candidates": [
        { "id": 1, "name": "강아지", "emoji": "🐶", "desc": "충성스러운 인간의 친구" },
        { "id": 2, "name": "고양이", "emoji": "🐱", "desc": "도도하지만 귀여운" },
        { "id": 3, "name": "토끼", "emoji": "🐰", "desc": "폭신폭신 솜털 뭉치" },
        { "id": 4, "name": "판다", "emoji": "🐼", "desc": "흑백의 대나무 요정" },
        { "id": 5, "name": "수달", "emoji": "🦦", "desc": "물에서 노는 귀요미" },
        { "id": 6, "name": "펭귄", "emoji": "🐧", "desc": "뒤뚱뒤뚱 신사" },
        { "id": 7, "name": "햄스터", "emoji": "🐹", "desc": "볼주머니가 귀여워" },
        { "id": 8, "name": "알파카", "emoji": "🦙", "desc": "북실북실 털뭉치" },
        { "id": 9, "name": "여우", "emoji": "🦊", "desc": "영리하고 신비로운" },
        { "id": 10, "name": "돌고래", "emoji": "🐬", "desc": "바다의 지능왕" },
        { "id": 11, "name": "코알라", "emoji": "🐨", "desc": "유칼립투스 나무의 요정" },
        { "id": 12, "name": "카피바라", "emoji": "🦫", "desc": "세상 평화로운 대형 쥐" },
        { "id": 13, "name": "고슴도치", "emoji": "🦔", "desc": "가시 속에 숨은 귀요미" },
        { "id": 14, "name": "치타", "emoji": "🐆", "desc": "가장 빠른 육상 동물" },
        { "id": 15, "name": "레서판다", "emoji": "🦝", "desc": "빨간 판다의 귀여움" },
        { "id": 16, "name": "물개", "emoji": "🦭", "desc": "박수 치는 바다 개그맨" }
      ]
    },
    {
      "id": "hobby",
      "name": "취미 월드컵",
      "emoji": "🎨",
      "description": "최고의 취미 활동은?",
      "candidates": [
        { "id": 1, "name": "넷플릭스", "emoji": "📺", "desc": "드라마 정주행의 쾌감" },
        { "id": 2, "name": "게임", "emoji": "🎮", "desc": "가상 세계의 모험" },
        { "id": 3, "name": "운동", "emoji": "💪", "desc": "땀 흘리는 건강한 시간" },
        { "id": 4, "name": "독서", "emoji": "📚", "desc": "책 속으로 빠져들기" },
        { "id": 5, "name": "요리", "emoji": "👨‍🍳", "desc": "나만의 레시피 개발" },
        { "id": 6, "name": "여행", "emoji": "✈️", "desc": "새로운 곳에서 충전" },
        { "id": 7, "name": "카페탐방", "emoji": "☕", "desc": "숨겨진 카페 발굴" },
        { "id": 8, "name": "음악감상", "emoji": "🎵", "desc": "음악에 빠져드는 시간" },
        { "id": 9, "name": "그림그리기", "emoji": "🎨", "desc": "감성을 캔버스에" },
        { "id": 10, "name": "사진찍기", "emoji": "📸", "desc": "순간을 영원히" },
        { "id": 11, "name": "캠핑", "emoji": "⛺", "desc": "자연 속의 힐링" },
        { "id": 12, "name": "등산", "emoji": "🏔️", "desc": "정상에서의 성취감" },
        { "id": 13, "name": "쇼핑", "emoji": "🛍️", "desc": "득템의 짜릿함" },
        { "id": 14, "name": "영화관", "emoji": "🎬", "desc": "큰 화면과 서라운드" },
        { "id": 15, "name": "보드게임", "emoji": "🎲", "desc": "친구들과 두뇌 싸움" },
        { "id": 16, "name": "악기연주", "emoji": "🎸", "desc": "선율로 감정 표현" }
      ]
    },
    {
      "id": "season",
      "name": "계절 월드컵",
      "emoji": "🌸",
      "description": "가장 좋아하는 계절 순간은?",
      "candidates": [
        { "id": 1, "name": "벚꽃시즌", "emoji": "🌸", "desc": "분홍빛 꽃비가 내려" },
        { "id": 2, "name": "해수욕장", "emoji": "🏖️", "desc": "파도 소리와 모래사장" },
        { "id": 3, "name": "단풍놀이", "emoji": "🍂", "desc": "붉게 물든 가을 산" },
        { "id": 4, "name": "첫눈", "emoji": "❄️", "desc": "올겨울 첫 눈송이" },
        { "id": 5, "name": "크리스마스", "emoji": "🎄", "desc": "반짝이는 겨울 축제" },
        { "id": 6, "name": "가을캠핑", "emoji": "🏕️", "desc": "낙엽 밟으며 캠파이어" },
        { "id": 7, "name": "여름밤", "emoji": "🌙", "desc": "열대야의 낭만" },
        { "id": 8, "name": "봄소풍", "emoji": "🧺", "desc": "새싹 돋는 들판에서" },
        { "id": 9, "name": "겨울온천", "emoji": "♨️", "desc": "눈 내리는 노천탕" },
        { "id": 10, "name": "여름축제", "emoji": "🎆", "desc": "불꽃놀이와 야시장" },
        { "id": 11, "name": "가을독서", "emoji": "📖", "desc": "낙엽 소리에 책 한 권" },
        { "id": 12, "name": "봄나들이", "emoji": "🌼", "desc": "꽃향기 따라 산책" },
        { "id": 13, "name": "눈싸움", "emoji": "⛄", "desc": "눈밭에서 어린이로" },
        { "id": 14, "name": "수박", "emoji": "🍉", "desc": "여름 한 입의 시원함" },
        { "id": 15, "name": "군고구마", "emoji": "🍠", "desc": "겨울 길거리 간식" },
        { "id": 16, "name": "장마", "emoji": "🌧️", "desc": "빗소리 들으며 낮잠" }
      ]
    },
    {
      "id": "dessert",
      "name": "디저트 월드컵",
      "emoji": "🍰",
      "description": "가장 맛있는 디저트를 찾아라!",
      "candidates": [
        { "id": 1, "name": "아이스크림", "emoji": "🍦", "desc": "달콤한 여름의 필수품" },
        { "id": 2, "name": "케이크", "emoji": "🎂", "desc": "촉촉하고 달콤한 레이어" },
        { "id": 3, "name": "마카롱", "emoji": "🫐", "desc": "파리지앵 감성 쿠키" },
        { "id": 4, "name": "초콜릿", "emoji": "🍫", "desc": "행복 호르몬 폭발" },
        { "id": 5, "name": "붕어빵", "emoji": "🐟", "desc": "팥이냐 크림이냐" },
        { "id": 6, "name": "호떡", "emoji": "🥞", "desc": "달콤한 겨울 거리 간식" },
        { "id": 7, "name": "크레페", "emoji": "🫔", "desc": "얇은 반죽에 달콤함" },
        { "id": 8, "name": "와플", "emoji": "🧇", "desc": "바삭하고 달콤한 격자" },
        { "id": 9, "name": "도넛", "emoji": "🍩", "desc": "글레이즈 코팅의 유혹" },
        { "id": 10, "name": "타르트", "emoji": "🥧", "desc": "바삭한 껍질 위의 과일" },
        { "id": 11, "name": "쿠키", "emoji": "🍪", "desc": "갓 구운 버터 향기" },
        { "id": 12, "name": "푸딩", "emoji": "🍮", "desc": "부들부들 카라멜 소스" },
        { "id": 13, "name": "티라미수", "emoji": "☕", "desc": "커피와 마스카포네" },
        { "id": 14, "name": "브라우니", "emoji": "🍫", "desc": "진한 초코 덩어리" },
        { "id": 15, "name": "크로플", "emoji": "🥐", "desc": "크루아상 + 와플 조합" },
        { "id": 16, "name": "허니버터칩", "emoji": "🍯", "desc": "달콤 짭짤 중독 과자" }
      ]
    }
  ]
}
